{"concurrency.md":"ucYUJzAS","index.md":"OfuGNhK4","modules_autoc.md":"Cn7w-zXp","modules_chart.md":"Chs-thee","modules_dailygainers.md":"CRYdeSE4","modules_dailylosers.md":"CSHVUWxg","modules_fundamentalstimeseries.md":"6CZd7lho","modules_historical.md":"Gk140s34","modules_insights.md":"B2gymhQI","modules_options.md":"CC-zXf-v","modules_quote.md":"BhwLgitl","modules_quotesummary.md":"BRxqZDDo","modules_recommendationsbysymbol.md":"Dce8x0z7","modules_screener.md":"CfpekmOo","modules_search.md":"CikpntZi","modules_trendingsymbols.md":"DjRxhGHU","other_quotecombine.md":"DPhb2h87","other_setglobalconfig.md":"B5yWSnbL","upgrading.md":"C2WdNAom","validation.md":"C9xNmCN2"}
